ailab/__init__.py
ailab/server/__init__.py
ailab/server/main.py
ailab/server/server.py
ailab/server/terminal_emulator.py
ailab-20210210.dist-info/LICENSE
ailab-20210210.dist-info/METADATA
ailab-20210210.dist-info/WHEEL
ailab-20210210.dist-info/entry_points.txt
ailab-20210210.dist-info/top_level.txt
ailab-20210210.dist-info/RECORD
