Metadata-Version: 2.1
Name: ailab
Version: 20210210
Summary: An environment to manage all your running ai experiments across multiple computers.
Home-page: https://github.com/penguinmenac3/ailab
Author: Michael Fuerst
Author-email: mail@michaelfuerst.de
License: BSD
Download-URL: https://github.com/penguinmenac3/ailab/tarball/20210210
Platform: UNKNOWN
Classifier: Development Status :: 3 - Alpha
Classifier: Intended Audience :: Developers
Classifier: Programming Language :: Python
Requires-Dist: matplotlib
Requires-Dist: pillow
Requires-Dist: scipy
Requires-Dist: scikit-image
Requires-Dist: numpy
Requires-Dist: GPUtil
Requires-Dist: psutil
Requires-Dist: cefpython3 (==66.0)
Requires-Dist: pyte
Requires-Dist: entangle-python
Requires-Dist: rempy
